<?xml version="1.0" encoding="utf-8"?>
<LanguageData>
  <!--The following translations were generated by https://www.deepl.com/-->
  <!-- EN: Asphalt -->
  <SadjuukAsphaltFloorAA.label>Asphalte</SadjuukAsphaltFloorAA.label>
  <!-- EN: Asphalt Floor, usually for roads or outdoor storage area. -->
  <SadjuukAsphaltFloorAA.description>Sol en asphalte, généralement pour les routes ou les aires de stockage extérieures.</SadjuukAsphaltFloorAA.description>
  <!-- EN: Dark Asphalt -->
  <SadjuukAsphaltFloorAB.label>Asphalte sombre</SadjuukAsphaltFloorAB.label>
  <SadjuukAsphaltFloorAB.description>Sol en asphalte, généralement pour les routes ou les aires de stockage extérieures.</SadjuukAsphaltFloorAB.description>
  <!-- EN: Concrete Floor -->
  <SadjuukConcreteFloorA.label>Sol en béton</SadjuukConcreteFloorA.label>
  <!-- EN: Concrete Floor. -->
  <SadjuukConcreteFloorA.description>Sol en béton.</SadjuukConcreteFloorA.description>
  <!-- EN: Painted Concrete Floor A -->
  <SadjuukConcreteFloorAA.label>Sol en béton peint A</SadjuukConcreteFloorAA.label>
  <!-- EN: Painted concrete Floor. -->
  <SadjuukConcreteFloorAA.description>Sol en béton peint.</SadjuukConcreteFloorAA.description>
  <!-- EN: Painted Concrete Floor B -->
  <SadjuukConcreteFloorAB.label>Sol en béton peint B</SadjuukConcreteFloorAB.label>
  <SadjuukConcreteFloorAB.description>Sol en béton peint.</SadjuukConcreteFloorAB.description>
  <!-- EN: Painted Concrete Floor C -->
  <SadjuukConcreteFloorAC.label>Sol en béton peint C</SadjuukConcreteFloorAC.label>
  <SadjuukConcreteFloorAC.description>Sol en béton peint.</SadjuukConcreteFloorAC.description>
  <!-- EN: Painted Concrete Floor D -->
  <SadjuukConcreteFloorAD.label>Sol en béton peint D</SadjuukConcreteFloorAD.label>
  <SadjuukConcreteFloorAD.description>Sol en béton peint.</SadjuukConcreteFloorAD.description>
  <!-- EN: Painted Concrete Floor E -->
  <SadjuukConcreteFloorAE.label>Sol en béton peint E</SadjuukConcreteFloorAE.label>
  <SadjuukConcreteFloorAE.description>Sol en béton peint.</SadjuukConcreteFloorAE.description>
  <!-- EN: Painted Concrete Floor F -->
  <SadjuukConcreteFloorAF.label>Sol en béton peint F</SadjuukConcreteFloorAF.label>
  <SadjuukConcreteFloorAF.description>Sol en béton peint.</SadjuukConcreteFloorAF.description>
  <!-- EN: Painted Concrete Floor G -->
  <SadjuukConcreteFloorAG.label>Sol en béton peint G</SadjuukConcreteFloorAG.label>
  <SadjuukConcreteFloorAG.description>Sol en béton peint.</SadjuukConcreteFloorAG.description>
  <!-- EN: Painted Concrete Floor H -->
  <SadjuukConcreteFloorAH.label>Sol en béton peint H</SadjuukConcreteFloorAH.label>
  <SadjuukConcreteFloorAH.description>Sol en béton peint.</SadjuukConcreteFloorAH.description>
  <!-- EN: Painted Concrete Floor I -->
  <SadjuukConcreteFloorAI.label>Sol en béton peint I</SadjuukConcreteFloorAI.label>
  <SadjuukConcreteFloorAI.description>Sol en béton peint.</SadjuukConcreteFloorAI.description>
  <!-- EN: Painted Concrete Floor J -->
  <SadjuukConcreteFloorAJ.label>Sol en béton peint J</SadjuukConcreteFloorAJ.label>
  <SadjuukConcreteFloorAJ.description>Sol en béton peint.</SadjuukConcreteFloorAJ.description>
  <!-- EN: Painted Concrete Floor K -->
  <SadjuukConcreteFloorAK.label>Sol en béton peint K</SadjuukConcreteFloorAK.label>
  <SadjuukConcreteFloorAK.description>Sol en béton peint.</SadjuukConcreteFloorAK.description>
  <!-- EN: Painted Concrete Floor L -->
  <SadjuukConcreteFloorAL.label>Sol en béton peint L</SadjuukConcreteFloorAL.label>
  <SadjuukConcreteFloorAL.description>Sol en béton peint.</SadjuukConcreteFloorAL.description>
  <!-- EN: Painted Concrete Floor M -->
  <SadjuukConcreteFloorAM.label>Sol en béton peint M</SadjuukConcreteFloorAM.label>
  <SadjuukConcreteFloorAM.description>Sol en béton peint.</SadjuukConcreteFloorAM.description>
  <!-- EN: Painted Concrete Floor N -->
  <SadjuukConcreteFloorAN.label>Sol en béton peint N</SadjuukConcreteFloorAN.label>
  <SadjuukConcreteFloorAN.description>Sol en béton peint.</SadjuukConcreteFloorAN.description>
  <!-- EN: Painted Steel Floor A -->
  <SadjuukConcreteFloorCA.label>Plancher en acier peint A</SadjuukConcreteFloorCA.label>
  <!-- EN: An aesthetic painted Steel Floor for hospital, kitchens or industrial complex. \nVery strong conception with its concrete foundation, the thick layer of paint makes it also very easy to clean. -->
  <SadjuukConcreteFloorCA.description>Un sol esthétique en acier peint pour les hôpitaux, les cuisines ou les complexes industriels.
De conception très solide grâce à sa fondation en béton, l'épaisse couche de peinture le rend également très facile à nettoyer.</SadjuukConcreteFloorCA.description>
  <!-- EN: Painted Steel Floor B -->
  <SadjuukConcreteFloorCB.label>Plancher en acier peint B</SadjuukConcreteFloorCB.label>
  <SadjuukConcreteFloorCB.description>Un sol esthétique en acier peint pour les hôpitaux, les cuisines ou les complexes industriels.
De conception très solide grâce à sa fondation en béton, l'épaisse couche de peinture le rend également très facile à nettoyer.</SadjuukConcreteFloorCB.description>
  <!-- EN: Painted Steel Floor C -->
  <SadjuukConcreteFloorCC.label>Plancher en acier peint C</SadjuukConcreteFloorCC.label>
  <SadjuukConcreteFloorCC.description>Un sol esthétique en acier peint pour les hôpitaux, les cuisines ou les complexes industriels.
De conception très solide grâce à sa fondation en béton, l'épaisse couche de peinture le rend également très facile à nettoyer.</SadjuukConcreteFloorCC.description>
  <!-- EN: Painted Steel Floor D -->
  <SadjuukConcreteFloorCD.label>Plancher en acier peint D</SadjuukConcreteFloorCD.label>
  <SadjuukConcreteFloorCD.description>Un sol esthétique en acier peint pour les hôpitaux, les cuisines ou les complexes industriels.
De conception très solide grâce à sa fondation en béton, l'épaisse couche de peinture le rend également très facile à nettoyer.</SadjuukConcreteFloorCD.description>
  <!-- EN: Painted Steel Floor E -->
  <SadjuukConcreteFloorCE.label>Plancher en acier peint E</SadjuukConcreteFloorCE.label>
  <SadjuukConcreteFloorCE.description>Un sol esthétique en acier peint pour les hôpitaux, les cuisines ou les complexes industriels.
De conception très solide grâce à sa fondation en béton, l'épaisse couche de peinture le rend également très facile à nettoyer.</SadjuukConcreteFloorCE.description>
  <!-- EN: Painted Steel Floor F -->
  <SadjuukConcreteFloorCF.label>Plancher en acier peint F</SadjuukConcreteFloorCF.label>
  <SadjuukConcreteFloorCF.description>Un sol esthétique en acier peint pour les hôpitaux, les cuisines ou les complexes industriels.
De conception très solide grâce à sa fondation en béton, l'épaisse couche de peinture le rend également très facile à nettoyer.</SadjuukConcreteFloorCF.description>
  <!-- EN: Painted Steel Floor G -->
  <SadjuukConcreteFloorCG.label>Plancher en acier peint G</SadjuukConcreteFloorCG.label>
  <SadjuukConcreteFloorCG.description>Un sol esthétique en acier peint pour les hôpitaux, les cuisines ou les complexes industriels.
De conception très solide grâce à sa fondation en béton, l'épaisse couche de peinture le rend également très facile à nettoyer.</SadjuukConcreteFloorCG.description>
  <!-- EN: Painted Steel Floor H -->
  <SadjuukConcreteFloorCH.label>Plancher en acier peint H</SadjuukConcreteFloorCH.label>
  <SadjuukConcreteFloorCH.description>Un sol esthétique en acier peint pour les hôpitaux, les cuisines ou les complexes industriels.
De conception très solide grâce à sa fondation en béton, l'épaisse couche de peinture le rend également très facile à nettoyer.</SadjuukConcreteFloorCH.description>
  <!-- EN: Painted Steel Floor I -->
  <SadjuukConcreteFloorCI.label>Plancher en acier peint I</SadjuukConcreteFloorCI.label>
  <SadjuukConcreteFloorCI.description>Un sol esthétique en acier peint pour les hôpitaux, les cuisines ou les complexes industriels.
De conception très solide grâce à sa fondation en béton, l'épaisse couche de peinture le rend également très facile à nettoyer.</SadjuukConcreteFloorCI.description>
  <!-- EN: Painted Steel Floor J -->
  <SadjuukConcreteFloorCJ.label>Plancher en acier peint J</SadjuukConcreteFloorCJ.label>
  <SadjuukConcreteFloorCJ.description>Un sol esthétique en acier peint pour les hôpitaux, les cuisines ou les complexes industriels.
De conception très solide grâce à sa fondation en béton, l'épaisse couche de peinture le rend également très facile à nettoyer.</SadjuukConcreteFloorCJ.description>
  <!-- EN: Painted Steel Floor K -->
  <SadjuukConcreteFloorCK.label>Plancher en acier peint K</SadjuukConcreteFloorCK.label>
  <SadjuukConcreteFloorCK.description>Un sol esthétique en acier peint pour les hôpitaux, les cuisines ou les complexes industriels.
De conception très solide grâce à sa fondation en béton, l'épaisse couche de peinture le rend également très facile à nettoyer.</SadjuukConcreteFloorCK.description>
  <!-- EN: Painted Steel Floor L -->
  <SadjuukConcreteFloorCL.label>Plancher en acier peint L</SadjuukConcreteFloorCL.label>
  <SadjuukConcreteFloorCL.description>Un sol esthétique en acier peint pour les hôpitaux, les cuisines ou les complexes industriels.
De conception très solide grâce à sa fondation en béton, l'épaisse couche de peinture le rend également très facile à nettoyer.</SadjuukConcreteFloorCL.description>
  <!-- EN: Painted Steel Floor M -->
  <SadjuukConcreteFloorCM.label>Plancher en acier peint M</SadjuukConcreteFloorCM.label>
  <SadjuukConcreteFloorCM.description>Un sol esthétique en acier peint pour les hôpitaux, les cuisines ou les complexes industriels.
De conception très solide grâce à sa fondation en béton, l'épaisse couche de peinture le rend également très facile à nettoyer.</SadjuukConcreteFloorCM.description>
  <!-- EN: Painted Steel Floor N -->
  <SadjuukConcreteFloorCN.label>Plancher en acier peint N</SadjuukConcreteFloorCN.label>
  <SadjuukConcreteFloorCN.description>Un sol esthétique en acier peint pour les hôpitaux, les cuisines ou les complexes industriels.
De conception très solide grâce à sa fondation en béton, l'épaisse couche de peinture le rend également très facile à nettoyer.</SadjuukConcreteFloorCN.description>
  <!-- EN: Painted Steel Floor O -->
  <SadjuukConcreteFloorCO.label>Plancher en acier peint O</SadjuukConcreteFloorCO.label>
  <SadjuukConcreteFloorCO.description>Un sol esthétique en acier peint pour les hôpitaux, les cuisines ou les complexes industriels.
De conception très solide grâce à sa fondation en béton, l'épaisse couche de peinture le rend également très facile à nettoyer.</SadjuukConcreteFloorCO.description>
  <!-- EN: Painted Steel Floor P -->
  <SadjuukConcreteFloorCP.label>Plancher en acier peint P</SadjuukConcreteFloorCP.label>
  <SadjuukConcreteFloorCP.description>Un sol esthétique en acier peint pour les hôpitaux, les cuisines ou les complexes industriels.
De conception très solide grâce à sa fondation en béton, l'épaisse couche de peinture le rend également très facile à nettoyer.</SadjuukConcreteFloorCP.description>
  <!-- EN: Painted Steel Floor Q -->
  <SadjuukConcreteFloorCQ.label>Plancher en acier peint Q</SadjuukConcreteFloorCQ.label>
  <SadjuukConcreteFloorCQ.description>Un sol esthétique en acier peint pour les hôpitaux, les cuisines ou les complexes industriels.
De conception très solide grâce à sa fondation en béton, l'épaisse couche de peinture le rend également très facile à nettoyer.</SadjuukConcreteFloorCQ.description>
  <!-- EN: Metal Grid Floor -->
  <SadjuukSteelFloorAA.label>Plancher en grille métallique</SadjuukSteelFloorAA.label>
  <!-- EN: Raw Metal Floor, inexpensive and quick to build, but ugly. -->
  <SadjuukSteelFloorAA.description>Plancher en métal brut, peu coûteux et rapide à construire, mais laid.</SadjuukSteelFloorAA.description>
  <!-- EN: Metal Plate Floor -->
  <SadjuukSteelFloorAB.label>Plancher en plaques de métal</SadjuukSteelFloorAB.label>
  <SadjuukSteelFloorAB.description>Plancher en métal brut, peu coûteux et rapide à construire, mais laid.</SadjuukSteelFloorAB.description>
  <!-- EN: Wood Floor A -->
  <SadjuukWoodFloorAA.label>Parquet A</SadjuukWoodFloorAA.label>
  <!-- EN: Simple wooden flooring, made of wooden logs. -->
  <SadjuukWoodFloorAA.description>Plancher en bois simple, fait de rondins de bois.</SadjuukWoodFloorAA.description>
  <!-- EN: Wood Floor B -->
  <SadjuukWoodFloorAB.label>Parquet B</SadjuukWoodFloorAB.label>
  <SadjuukWoodFloorAB.description>Plancher en bois simple, fait de rondins de bois.</SadjuukWoodFloorAB.description>
  <!-- EN: Wood Floor C -->
  <SadjuukWoodFloorAC.label>Parquet C</SadjuukWoodFloorAC.label>
  <SadjuukWoodFloorAC.description>Plancher en bois simple, fait de rondins de bois.</SadjuukWoodFloorAC.description>
  <!-- EN: Wood Floor D -->
  <SadjuukWoodFloorAD.label>Parquet D</SadjuukWoodFloorAD.label>
  <SadjuukWoodFloorAD.description>Plancher en bois simple, fait de rondins de bois.</SadjuukWoodFloorAD.description>
  <!-- EN: Wood Floor E -->
  <SadjuukWoodFloorAE.label>Parquet E</SadjuukWoodFloorAE.label>
  <SadjuukWoodFloorAE.description>Plancher en bois simple, fait de rondins de bois.</SadjuukWoodFloorAE.description>
  <!-- EN: Wood Floor F -->
  <SadjuukWoodFloorAF.label>Parquet F</SadjuukWoodFloorAF.label>
  <SadjuukWoodFloorAF.description>Plancher en bois simple, fait de rondins de bois.</SadjuukWoodFloorAF.description>
  <SadjuukWoodFloorBA.label>Parquet A</SadjuukWoodFloorBA.label>
  <!-- EN: Simple wooden flooring, made of wood planks. -->
  <SadjuukWoodFloorBA.description>Plancher en bois simple, fait de planches de bois.</SadjuukWoodFloorBA.description>
  <SadjuukWoodFloorBB.label>Parquet B</SadjuukWoodFloorBB.label>
  <SadjuukWoodFloorBB.description>Plancher en bois simple, fait de planches de bois.</SadjuukWoodFloorBB.description>
  <SadjuukWoodFloorBC.label>Parquet C</SadjuukWoodFloorBC.label>
  <SadjuukWoodFloorBC.description>Plancher en bois simple, fait de planches de bois.</SadjuukWoodFloorBC.description>
  <SadjuukWoodFloorBD.label>Parquet D</SadjuukWoodFloorBD.label>
  <SadjuukWoodFloorBD.description>Plancher en bois simple, fait de planches de bois.</SadjuukWoodFloorBD.description>
  <SadjuukWoodFloorBE.label>Parquet E</SadjuukWoodFloorBE.label>
  <SadjuukWoodFloorBE.description>Plancher en bois simple, fait de planches de bois.</SadjuukWoodFloorBE.description>
  <SadjuukWoodFloorBF.label>Parquet F</SadjuukWoodFloorBF.label>
  <SadjuukWoodFloorBF.description>Plancher en bois simple, fait de planches de bois.</SadjuukWoodFloorBF.description>
</LanguageData>
